{"sections":{"main":{"type":"main-product","blocks":{"title":{"type":"title","settings":{}},"ht_micro_trust_strip_tTgtGM":{"type":"ht_micro_trust_strip","settings":{"bg":"#0f3a2f","text":"#ffffff","muted":"#9aa7a2","border":"#1e4a3f","item1_svg":"","item1_emoji":"{{ product.metafields.custom.product_microstrip_svg1.value }}","item1_heading":"{{ product.metafields.custom.product_microstrip1.value }}","item2_svg":"","item2_emoji":"{{ product.metafields.custom.product_microstrip_svg2.value }}","item2_heading":"{{ product.metafields.custom.product_microstrip2.value }}","item3_svg":"","item3_emoji":"{{ product.metafields.custom.product_microstrip_svg3.value }}","item3_heading":"{{ product.metafields.custom.product_microstrip3.value }}"}},"buy_buttons":{"type":"buy_buttons","settings":{"show_dynamic_checkout":false,"show_gift_card_recipient":true}}},"block_order":["title","ht_micro_trust_strip_tTgtGM","buy_buttons"],"settings":{"enable_sticky_info":true,"color_scheme":"background-2","media_size":"small","constrain_to_viewport":true,"media_fit":"contain","gallery_layout":"thumbnail","mobile_thumbnails":"show","media_position":"left","image_zoom":"none","hide_variants":true,"enable_video_looping":true,"padding_top":36,"padding_bottom":12}},"ht_bundle_info_MEVK7g":{"type":"ht-bundle-info","name":"HT • Bundle Info","settings":{"limit_to_bundles":true,"show_whats_inside":true,"whats_inside_open_default":false,"whats_inside_title":"What’s inside this bundle","whats_inside_item_1":"Everyday Jar – 2oz whipped tallow for face & body.","whats_inside_item_2":"On The Go Tin – 1oz travel-size balm for pockets and bags.","whats_inside_item_3":"Pocket Stick – concentrated tallow stick for lips and dry spots.","show_how_it_works":true,"how_open_default":false,"how_it_works_title":"How it works","how_item_1":"Choose 1 scent for your Everyday Jar.","how_item_2":"Choose 1 scent for your On The Go Tin.","how_item_3":"Choose 1 scent for your Pocket Stick.","how_item_4":"20% off applies automatically once all three are in your cart.","show_why_bundle":true,"why_open_default":false,"why_bundle_title":"Why start with this kit","why_item_1":"Try all three formats – jar, tin, and stick.","why_item_2":"Dial in your personal scent combo.","why_item_3":"Save 20% on a full everyday routine.","show_faq":true,"faq_open_default":false,"faq_title":"Quick questions","faq_q1":"Can I mix scents?","faq_a1":"Yes—each product in the kit can have its own scent.","faq_q2":"Is the discount automatic?","faq_a2":"Yes—no code needed. Once all three are in your cart, 20% off applies to each.","faq_q3":"Is this good for sensitive skin?","faq_a3":"Our grass-fed tallow balm is naturally gentle and non-comedogenic.","v_margin_desktop":40,"v_margin_mobile":32}},"ht_nyh_jp3Rp4":{"type":"ht-nyh","name":"Nourish Your Hide","settings":{"title":"Nourish Your Hide","subtitle":"No hype. No filler. Just real ingredients that actually work — for you, your family, and your skin.","logo_width":300,"logo_opacity":0.1,"bg":"#fefcf9","heading_color":"#1a1a1a","text_color":"#444444"}},"ht_whyht_QJY4T8":{"type":"ht-whyht","blocks":{"pillar_JikkTK":{"type":"pillar","settings":{"heading":"Always Grass-Fed & Finished","body":"No shortcuts. Our tallow is 100% grass-fed, grass-finished, and sourced from trusted farms."}},"pillar_8DGztX":{"type":"pillar","settings":{"heading":"Actually Affordable","body":"Tired of $45 jars? Us too. We kept it real — real pricing, no gimmicks or markups."}},"pillar_XCXTtA":{"type":"pillar","settings":{"heading":"Made in the USA","body":"Poured, packed, and shipped right here — supporting small farms and suppliers across the U.S."}},"pillar_rtb6Hb":{"type":"pillar","settings":{"heading":"Built by Real People","body":"We started Hide out of frustration with overpriced, overcomplicated “natural” skincare. So we fixed it."}},"pillar_nBa6Mb":{"type":"pillar","settings":{"heading":"No Fluff. No Fillers.","body":"Always pure, always powerful — priced right, with nothing extra."}}},"block_order":["pillar_JikkTK","pillar_8DGztX","pillar_XCXTtA","pillar_rtb6Hb","pillar_nBa6Mb"],"name":"Why Hide Tallow","settings":{"title":"Why Hide Tallow?","subtitle":"A different kind of skincare — made for real people, priced for real life.","desktop_layout":"center","tile_width":220,"show_progress_bar":true,"bg":"#fefcf9","tile_bg":"#ffffff","heading_color":"#1a1a1a","text_color":"#555555","progress_color":"#000000","icon_size":40}},"related-products":{"type":"related-products","disabled":true,"settings":{"heading":"You may also like","heading_size":"h2","products_to_show":4,"columns_desktop":4,"columns_mobile":"2","color_scheme":"scheme-1","image_ratio":"square","image_shape":"default","show_secondary_image":true,"show_vendor":false,"show_rating":false,"padding_top":36,"padding_bottom":28}}},"order":["main","ht_bundle_info_MEVK7g","ht_nyh_jp3Rp4","ht_whyht_QJY4T8","related-products"]}